# 12.12 [DP, 리스트 컴프리헨션]

- DP 라고 한다면 top- down 혹은 bottom-up 방식으로 풀어야 할 지 고민해야 할 것 이다.
    - [파일 합치기](https://www.acmicpc.net/problem/11066) (최적 이진 검색 트리(Optimal Binary Search Tree))
        - 크누스 최적화 기법…
        - 현재 알고리즘 풀이로는 pypy3 로만 통과가 된다.
          
            ```python
            import sys
            input = sys.stdin.readline
            
            T = int(input()) # 테스트 케이스 T
            for _ in range(T):
                K = int(input()) # 소설 구성하는 장 수
                arr = [0] + list(map(int, input().split()))
            
                s = [0] * (K + 1) # 누적합
                s[1] = arr[1]
                for i in range(2, K + 1):
                    s[i] = s[i - 1] + arr[i]
                
                # dp[i][j] : i 번째 파일 부터 j 번째 파일을 합치는데 필요한 최소 비용
                dp = [[0] * (K + 1) for _ in range(K + 1)]
            
                for l in range(2, K + 1): # 합쳐진 길이 값
                    for i in range(1, (K + 1) - l + 1): # 시작 위치
                        # 해당 구간에서 잘리는 위치 j
                        tmp = []
                        for j in range(i, i + l - 1):
                            tmp.append(dp[i][j] + dp[j + 1][i + l - 1])
                        tmp.sort()
                        # 현재 구간 전 크기에서 가장 작은 비용을 가지고 오고
                        # 결국에 파일 합치는 비용은 현재 구간의 파일 크기 합 또한 더해줘야 하기 때문에
                        # min_v + 현재 구간 누적합(s[i + l - 1] - s[i - 1])이다.
                        min_v = tmp[0]
                        dp[i][i + l - 1] = min_v + s[i + l - 1] - s[i - 1]
            
                print(dp[1][K])
            ```
            
            - 구조는 같은 것 같은데 속도 차이가 2배 난다.
              
                ```python
                t = int(input())
                
                for _ in range(t):
                    k = int(input())
                    lst = [0] + list(map(int,input().split()))
                
                    s_lst = [0 for _ in range(k+1)]
                
                    for i in range(1,k+1):
                        s_lst[i] = s_lst[i-1] + lst[i]
                    # print('s_lst',s_lst)
                
                    dp = [[0 for i in range(k+1)] for j in range(k+1)]
                
                    for i in range(2,k+1):
                        for j in range(1,k+2-i):
                            dp[j][j+i-1] = min([dp[j][j+q] + dp[j+q+1][j+i-1] for q in range(i-1)]) +(s_lst[j+i-1] - s_lst[j-1])
                    print(dp[1][k])
                ```
                
            - 차이점
                - 누적합 s 를 list-comprehension으로 만들었다.
                - min_v 를 구할 때, 리스트 컴프리헨션으로 구성했다.
                    - **컴프리헨션**
                        - 원하는 데이터를 파이썬에서 제공하는 자료구조(list, dictionary, set)에 담아 표현하려할 때 사용할 수 있는 문법으로 종류는 4가지이다.
                          
                            1. List Comprehension
                            
                            2. Dictionary Comprehension
                            
                            3. Set Comprehension
                            
                            4. Generator Comprehension
                            
                
                - **왜 이것이 더 빠른 걸까?**
                  
                    → 같은 식이라도 List Comprehension을 사용한 반복문의 속도가 훨씬 빠르다는 것이다.
                    
                - **List comprehension의 속도가 빠른 이유**
                    - 참조 : [https://whatisand.github.io/why-fast-list-comprehension-python/](https://whatisand.github.io/why-fast-list-comprehension-python/)
                    - 컴프리헨션 문법은 파이썬에서 속도 최적화가 되어있기 때문이다.
                    - 파이썬은 스크립트 언어이지만 실행하기 전에 자체 엔진에서 해석할 수 있는 바이너리 코드로 변환(컴파일)됩니다.
                    - **list append 와 list comprehension의 바이트 코드 비교**
                        - **list append**
                          
                            ```bash
                            >>> import dis
                            >>> def use_append():
                            ...     result = []
                            ...     for i in range(10000):
                            ...             result.append(i)
                            ...     return result
                            ...
                            >>> dis.dis(use_append)
                              2           0 BUILD_LIST               0
                                          2 STORE_FAST               0 (result)
                            
                              3           4 LOAD_GLOBAL              0 (range)
                                          6 LOAD_CONST               1 (10000)
                                          8 CALL_FUNCTION            1
                                         10 GET_ITER
                                    >>   12 FOR_ITER                14 (to 28)
                                         14 STORE_FAST               1 (i)
                            
                              4          16 LOAD_FAST                0 (result)
                                         18 LOAD_METHOD              1 (append)
                                         20 LOAD_FAST                1 (i)
                                         22 CALL_METHOD              1
                                         24 POP_TOP
                                         26 JUMP_ABSOLUTE           12
                            
                              5     >>   28 LOAD_FAST                0 (result)
                                         30 RETURN_VALUE
                            ```
                            
                        - **list comprehension**
                          
                            ```bash
                            >>> def use_compre():
                            ...     return [i for i in range(10000)]
                            ...
                            >>> dis.dis(use_compre)
                              2           0 LOAD_CONST               1 (<code object <listcomp> at 0x7fe36818f870, file "<stdin>", line 2>)
                                          2 LOAD_CONST               2 ('use_compre.<locals>.<listcomp>')
                                          4 MAKE_FUNCTION            0
                                          6 LOAD_GLOBAL              0 (range)
                                          8 LOAD_CONST               3 (10000)
                                         10 CALL_FUNCTION            1
                                         12 GET_ITER
                                         14 CALL_FUNCTION            1
                                         16 RETURN_VALUE
                            
                            Disassembly of <code object <listcomp> at 0x7fe36818f870, file "<stdin>", line 2>:
                              2           0 BUILD_LIST               0
                                          2 LOAD_FAST                0 (.0)
                                    >>    4 FOR_ITER                 8 (to 14)
                                          6 STORE_FAST               1 (i)
                                          8 LOAD_FAST                1 (i)
                                         10 LIST_APPEND              2
                                         12 JUMP_ABSOLUTE            4
                                    >>   14 RETURN_VALUE
                            ```
                            
                            - list append 방식에서는 **`CALL_METHOD`**를 통해 append 메소드를 사용합니다. 그렇다면 **`CALL_METHOD`** 로직을 타면서 생기는 비효율이 있지 않을까 생각해볼 수 있습니다.
                                - 빈 함수를 불러오는 for loop와 아무 것도 실행되지 않는 for loop를 도는 시간차이를 비교해 보았다.
                                  
                                    ```python
                                    % python3 -m timeit -s "def empty(): pass" "for i in range(10000000): empty()"
                                    1 loop, best of 5: 665 msec per loop
                                    
                                    % python3 -m timeit "for i in range(10000000): pass"
                                    2 loops, best of 5: 189 msec per loop
                                    ```
                                    
                                    - 실제로 엄청난 차이가 발생한다.
                        
                        <aside>
                        💡 **파이썬이 특정 메소드를 불러올 때 생기는 오버헤드에서 생겨난 것이라고 할 수 있습니다.**
                        
                        </aside>
                        
        
    - [**우유 도시**](https://www.acmicpc.net/problem/14722)